{
  "trade_date": "20260617",
  "min_boards": 2,
  "hist_pairs": 20,
  "calibration": {
    "lookback_pairs": 38,
    "min_boards": 2,
    "laplace_alpha": 1.0,
    "shrink_to_overall": 0.15,
    "board_rates": {
      "2": 0.2669583118888317,
      "3": 0.3518479033404406,
      "4": 0.2572330654420207,
      "5": 0.3152985074626865,
      "6": 0.1630597014925373
    },
    "overall_ge2_rate": 0.2835820895522388,
    "factor_multipliers": {
      "early_seal": 1.0121,
      "zero_zhaban": 1.08,
      "heavy_seal": 1.08,
      "big_order_seal": 0.9866,
      "weak_to_strong": 0.92
    },
    "backtest_summary": {
      "source": "15d_empirical_recalibration",
      "trade_days": 39,
      "stock_samples": 201,
      "actual_promotion_rate": 0.2835820895522388,
      "brier_before": 0.1963420939422876,
      "brier_after": 0.19472540728577367,
      "pair_days": [
        "20260427",
        "20260428",
        "20260429",
        "20260430",
        "20260506",
        "20260507",
        "20260508",
        "20260511",
        "20260512",
        "20260513",
        "20260514",
        "20260515",
        "20260518",
        "20260519",
        "20260520",
        "20260521",
        "20260522",
        "20260525",
        "20260526",
        "20260527",
        "20260528",
        "20260529",
        "20260601",
        "20260602",
        "20260603",
        "20260604",
        "20260605",
        "20260608",
        "20260609",
        "20260610",
        "20260611",
        "20260612",
        "20260615",
        "20260616",
        "20260617",
        "20260618",
        "20260622",
        "20260623",
        "20260624"
      ]
    }
  },
  "rates_by_board": {
    "1": {
      "n": 1,
      "total": 414,
      "promoted": 56,
      "rate": 0.13526570048309178
    },
    "2": {
      "n": 2,
      "total": 60,
      "promoted": 20,
      "rate": 0.2669583118888317,
      "calibrated": true
    },
    "3": {
      "n": 3,
      "total": 11,
      "promoted": 4,
      "rate": 0.3518479033404406,
      "calibrated": true
    },
    "4": {
      "n": 4,
      "total": 5,
      "promoted": 0,
      "rate": 0.2572330654420207,
      "calibrated": true
    },
    "5": {
      "n": 5,
      "total": 0,
      "promoted": 0,
      "rate": 0.3152985074626865,
      "calibrated": true
    },
    "6": {
      "n": 6,
      "total": 0,
      "promoted": 0,
      "rate": 0.1630597014925373,
      "calibrated": true
    }
  },
  "stocks": [
    {
      "代码": "600110",
      "名称": "诺德股份",
      "涨停原因": "铜箔+HVLP+固态电池+满产满销",
      "连板数": 3,
      "晋级概率": 0.4153611787292111,
      "封单占比": "214.5%",
      "大单封板": "强封",
      "弱转强": "否",
      "涨跌幅": "10.03%",
      "最新价": 17.22,
      "换手率": "0.93%",
      "封板资金": "5.99亿",
      "成交额": 279370304,
      "首次封板时间": "092500",
      "炸板次数": 0,
      "所属行业": "电池",
      "晋级概率_pct": 41.54,
      "题材簇": "行业:电池",
      "类似标的": "-"
    },
    {
      "代码": "601636",
      "名称": "旗滨集团",
      "涨停原因": "玻璃基板+浮法玻璃+光伏玻璃",
      "连板数": 3,
      "晋级概率": 0.4153611787292111,
      "封单占比": "35.7%",
      "大单封板": "强封",
      "弱转强": "否",
      "涨跌幅": "10.03%",
      "最新价": 8.67,
      "换手率": "2.20%",
      "封板资金": "2.01亿",
      "成交额": 563774048,
      "首次封板时间": "092503",
      "炸板次数": 0,
      "所属行业": "玻璃玻纤",
      "晋级概率_pct": 41.54,
      "题材簇": "行业:玻璃玻纤",
      "类似标的": "-"
    },
    {
      "代码": "002741",
      "名称": "光华科技",
      "涨停原因": "PCB化学品+AI算力+股权激励",
      "连板数": 3,
      "晋级概率": 0.4153611787292111,
      "封单占比": "23.8%",
      "大单封板": "强封",
      "弱转强": "否",
      "涨跌幅": "10.01%",
      "最新价": 39.44,
      "换手率": "4.83%",
      "封板资金": "1.92亿",
      "成交额": 806009472,
      "首次封板时间": "093012",
      "炸板次数": 0,
      "所属行业": "电子化学",
      "晋级概率_pct": 41.54,
      "题材簇": "磷化铟/半导体材料",
      "类似标的": "同线: 华正新材、宏昌电子、旭光电子 | 似近月龙头: 旭光电子"
    },
    {
      "代码": "600353",
      "名称": "旭光电子",
      "涨停原因": "氮化铝+韩国客户+真空灭弧室+可控核聚变",
      "连板数": 3,
      "晋级概率": 0.4153611787292111,
      "封单占比": "44.2%",
      "大单封板": "强封",
      "弱转强": "否",
      "涨跌幅": "9.99%",
      "最新价": 38.19,
      "换手率": "3.52%",
      "封板资金": "4.92亿",
      "成交额": 1113021728,
      "首次封板时间": "093035",
      "炸板次数": 0,
      "所属行业": "其他电子",
      "晋级概率_pct": 41.54,
      "题材簇": "磷化铟/半导体材料",
      "类似标的": "同线: 光华科技、华正新材、宏昌电子"
    },
    {
      "代码": "603618",
      "名称": "杭电股份",
      "涨停原因": "光纤涨价+铜箔+特高压",
      "连板数": 3,
      "晋级概率": 0.3845936840085288,
      "封单占比": "6.1%",
      "大单封板": "否",
      "弱转强": "否",
      "涨跌幅": "9.99%",
      "最新价": 51.73,
      "换手率": "4.48%",
      "封板资金": "9612.64万",
      "成交额": 1575478544,
      "首次封板时间": "093637",
      "炸板次数": 0,
      "所属行业": "电网设备",
      "晋级概率_pct": 38.46,
      "题材簇": "光纤/四氯化硅",
      "类似标的": "似近月龙头: 三孚股份、宏柏新材"
    },
    {
      "代码": "603115",
      "名称": "海星股份",
      "涨停原因": "AI服务器电极箔+市占率第一+业绩增长",
      "连板数": 3,
      "晋级概率": 0.3845936840085288,
      "封单占比": "5.2%",
      "大单封板": "否",
      "弱转强": "否",
      "涨跌幅": "10.00%",
      "最新价": 119.94,
      "换手率": "1.87%",
      "封板资金": "2746.63万",
      "成交额": 531354656,
      "首次封板时间": "093650",
      "炸板次数": 0,
      "所属行业": "元件",
      "晋级概率_pct": 38.46,
      "题材簇": "AI/算力/机器人",
      "类似标的": "同线: 艾华集团、鑫源智造 | 似近月龙头: 天娱数科"
    },
    {
      "代码": "000777",
      "名称": "中核科技",
      "涨停原因": "中核集团旗下+核电阀门+控股股东增持",
      "连板数": 3,
      "晋级概率": 0.3276168419331911,
      "封单占比": "4.6%",
      "大单封板": "否",
      "弱转强": "是",
      "涨跌幅": "10.02%",
      "最新价": 21.86,
      "换手率": "20.64%",
      "封板资金": "7841.84万",
      "成交额": 1701761984,
      "首次封板时间": "092500",
      "炸板次数": 2,
      "所属行业": "通用设备",
      "晋级概率_pct": 32.76,
      "题材簇": "行业:通用设备",
      "类似标的": "-"
    },
    {
      "代码": "603186",
      "名称": "华正新材",
      "涨停原因": "覆铜板+AI算力+定增扩产",
      "连板数": 3,
      "晋级概率": 0.3276168419331911,
      "封单占比": "1.0%",
      "大单封板": "否",
      "弱转强": "是",
      "涨跌幅": "10.00%",
      "最新价": 226.67,
      "换手率": "10.23%",
      "封板资金": "3538.32万",
      "成交额": 3603072160,
      "首次封板时间": "093256",
      "炸板次数": 33,
      "所属行业": "元件",
      "晋级概率_pct": 32.76,
      "题材簇": "磷化铟/半导体材料",
      "类似标的": "同线: 光华科技、宏昌电子、旭光电子 | 似近月龙头: 旭光电子"
    },
    {
      "代码": "603002",
      "名称": "宏昌电子",
      "涨停原因": "高速覆铜板+环氧树脂+先进封装",
      "连板数": 3,
      "晋级概率": 0.3276168419331911,
      "封单占比": "2.6%",
      "大单封板": "否",
      "弱转强": "是",
      "涨跌幅": "10.00%",
      "最新价": 23.2,
      "换手率": "6.92%",
      "封板资金": "4700.32万",
      "成交额": 1801844544,
      "首次封板时间": "093431",
      "炸板次数": 10,
      "所属行业": "电子化学",
      "晋级概率_pct": 32.76,
      "题材簇": "磷化铟/半导体材料",
      "类似标的": "同线: 光华科技、华正新材、旭光电子 | 似近月龙头: 旭光电子"
    },
    {
      "代码": "002080",
      "名称": "中材科技",
      "涨停原因": "特种电子布+风电叶片+央企背景",
      "连板数": 3,
      "晋级概率": 0.3276168419331911,
      "封单占比": "0.2%",
      "大单封板": "否",
      "弱转强": "是",
      "涨跌幅": "10.00%",
      "最新价": 82.41,
      "换手率": "4.92%",
      "封板资金": "1168.57万",
      "成交额": 6698619904,
      "首次封板时间": "094506",
      "炸板次数": 47,
      "所属行业": "玻璃玻纤",
      "晋级概率_pct": 32.76,
      "题材簇": "PCB/元件",
      "类似标的": "-"
    },
    {
      "代码": "603773",
      "名称": "沃格光电",
      "涨停原因": "TGV玻璃基板+先进封装+PET铜箔",
      "连板数": 2,
      "晋级概率": 0.2878934199797015,
      "封单占比": "14.4%",
      "大单封板": "是",
      "弱转强": "否",
      "涨跌幅": "10.00%",
      "最新价": 166.13,
      "换手率": "5.31%",
      "封板资金": "2.81亿",
      "成交额": 1950594960,
      "首次封板时间": "093914",
      "炸板次数": 0,
      "所属行业": "光学光电",
      "晋级概率_pct": 28.79,
      "题材簇": "磷化铟/半导体材料",
      "类似标的": "同线: 光华科技、华正新材、宏昌电子 | 似近月龙头: 旭光电子"
    },
    {
      "代码": "000679",
      "名称": "大连友谊",
      "涨停原因": "百货零售+大连地区+电商",
      "连板数": 2,
      "晋级概率": 0.28445155615028306,
      "封单占比": "17.9%",
      "大单封板": "是",
      "弱转强": "否",
      "涨跌幅": "10.03%",
      "最新价": 7.35,
      "换手率": "6.31%",
      "封板资金": "2830.61万",
      "成交额": 157769156,
      "首次封板时间": "130618",
      "炸板次数": 0,
      "所属行业": "一般零售",
      "晋级概率_pct": 28.45,
      "题材簇": "行业:一般零售",
      "类似标的": "-"
    },
    {
      "代码": "600192",
      "名称": "长城电工",
      "涨停原因": "输变电设备+核电+一带一路+国企改革",
      "连板数": 2,
      "晋级概率": 0.24857342686567163,
      "封单占比": "11.0%",
      "大单封板": "否",
      "弱转强": "是",
      "涨跌幅": "10.01%",
      "最新价": 8.35,
      "换手率": "6.66%",
      "封板资金": "2680.52万",
      "成交额": 243748936,
      "首次封板时间": "093122",
      "炸板次数": 3,
      "所属行业": "电网设备",
      "晋级概率_pct": 24.86,
      "题材簇": "行业:电网设备",
      "类似标的": "-"
    },
    {
      "代码": "600186",
      "名称": "莲花控股",
      "涨停原因": "算力+阶跃星辰投资+半导体材料+调味品龙头",
      "连板数": 2,
      "晋级概率": 0.24857342686567163,
      "封单占比": "1.9%",
      "大单封板": "否",
      "弱转强": "是",
      "涨跌幅": "9.98%",
      "最新价": 14.66,
      "换手率": "11.63%",
      "封板资金": "5748.95万",
      "成交额": 2988177536,
      "首次封板时间": "093633",
      "炸板次数": 8,
      "所属行业": "调味发酵",
      "晋级概率_pct": 24.86,
      "题材簇": "磷化铟/半导体材料",
      "类似标的": "同线: 光华科技、华正新材、宏昌电子 | 似近月龙头: 旭光电子"
    },
    {
      "代码": "002141",
      "名称": "贤丰控股",
      "涨停原因": "覆铜板+PCB上游+扭亏为盈",
      "连板数": 2,
      "晋级概率": 0.24857342686567163,
      "封单占比": "5.1%",
      "大单封板": "否",
      "弱转强": "是",
      "涨跌幅": "10.03%",
      "最新价": 4.28,
      "换手率": "16.09%",
      "封板资金": "3518.16万",
      "成交额": 687193168,
      "首次封板时间": "100554",
      "炸板次数": 6,
      "所属行业": "元件",
      "晋级概率_pct": 24.86,
      "题材簇": "磷化铟/半导体材料",
      "类似标的": "同线: 光华科技、华正新材、宏昌电子 | 似近月龙头: 旭光电子"
    },
    {
      "代码": "002989",
      "名称": "中天精装",
      "涨停原因": "FCBGA封装基板+HBM+半导体转型+浙江国资",
      "连板数": 2,
      "晋级概率": 0.24857342686567163,
      "封单占比": "0.8%",
      "大单封板": "否",
      "弱转强": "是",
      "涨跌幅": "10.01%",
      "最新价": 33.97,
      "换手率": "12.11%",
      "封板资金": "574.77万",
      "成交额": 739530528,
      "首次封板时间": "101718",
      "炸板次数": 17,
      "所属行业": "装修装饰",
      "晋级概率_pct": 24.86,
      "题材簇": "磷化铟/半导体材料",
      "类似标的": "同线: 光华科技、华正新材、宏昌电子 | 似近月龙头: 旭光电子"
    },
    {
      "代码": "600397",
      "名称": "江钨装备",
      "涨停原因": "钨钽铌并购+磁选装备+江西国资",
      "连板数": 2,
      "晋级概率": 0.24560164693772515,
      "封单占比": "0.0%",
      "大单封板": "否",
      "弱转强": "是",
      "涨跌幅": "10.01%",
      "最新价": 18.36,
      "换手率": "14.73%",
      "封板资金": "72.71万",
      "成交额": 2570234416,
      "首次封板时间": "131518",
      "炸板次数": 16,
      "所属行业": "专用设备",
      "晋级概率_pct": 24.56,
      "题材簇": "锆/小金属",
      "类似标的": "-"
    },
    {
      "代码": "600615",
      "名称": "鑫源智造",
      "涨停原因": "智能割草机器人+无人割草机+轻量化+比亚迪概念",
      "连板数": 2,
      "晋级概率": 0.24560164693772515,
      "封单占比": "1.1%",
      "大单封板": "否",
      "弱转强": "是",
      "涨跌幅": "9.96%",
      "最新价": 11.04,
      "换手率": "6.51%",
      "封板资金": "159.06万",
      "成交额": 151346554,
      "首次封板时间": "145008",
      "炸板次数": 1,
      "所属行业": "工业金属",
      "晋级概率_pct": 24.56,
      "题材簇": "AI/算力/机器人",
      "类似标的": "同线: 海星股份、艾华集团 | 似近月龙头: 天娱数科"
    },
    {
      "代码": "603989",
      "名称": "艾华集团",
      "涨停原因": "MLPC+AI服务器+铝电解电容+薄膜电容",
      "连板数": 2,
      "晋级概率": 0.24524254294567163,
      "封单占比": "12.2%",
      "大单封板": "是",
      "弱转强": "是",
      "涨跌幅": "10.00%",
      "最新价": 37.73,
      "换手率": "3.72%",
      "封板资金": "6685.90万",
      "成交额": 547646672,
      "首次封板时间": "093819",
      "炸板次数": 4,
      "所属行业": "元件",
      "晋级概率_pct": 24.52,
      "题材簇": "AI/算力/机器人",
      "类似标的": "同线: 海星股份、鑫源智造 | 似近月龙头: 天娱数科"
    }
  ],
  "by_boards": {
    "3": [
      {
        "代码": "600110",
        "名称": "诺德股份",
        "涨停原因": "铜箔+HVLP+固态电池+满产满销",
        "连板数": 3,
        "晋级概率": 0.4153611787292111,
        "封单占比": "214.5%",
        "大单封板": "强封",
        "弱转强": "否",
        "涨跌幅": "10.03%",
        "最新价": 17.22,
        "换手率": "0.93%",
        "封板资金": "5.99亿",
        "成交额": 279370304,
        "首次封板时间": "092500",
        "炸板次数": 0,
        "所属行业": "电池",
        "晋级概率_pct": 41.54,
        "题材簇": "行业:电池",
        "类似标的": "-"
      },
      {
        "代码": "601636",
        "名称": "旗滨集团",
        "涨停原因": "玻璃基板+浮法玻璃+光伏玻璃",
        "连板数": 3,
        "晋级概率": 0.4153611787292111,
        "封单占比": "35.7%",
        "大单封板": "强封",
        "弱转强": "否",
        "涨跌幅": "10.03%",
        "最新价": 8.67,
        "换手率": "2.20%",
        "封板资金": "2.01亿",
        "成交额": 563774048,
        "首次封板时间": "092503",
        "炸板次数": 0,
        "所属行业": "玻璃玻纤",
        "晋级概率_pct": 41.54,
        "题材簇": "行业:玻璃玻纤",
        "类似标的": "-"
      },
      {
        "代码": "002741",
        "名称": "光华科技",
        "涨停原因": "PCB化学品+AI算力+股权激励",
        "连板数": 3,
        "晋级概率": 0.4153611787292111,
        "封单占比": "23.8%",
        "大单封板": "强封",
        "弱转强": "否",
        "涨跌幅": "10.01%",
        "最新价": 39.44,
        "换手率": "4.83%",
        "封板资金": "1.92亿",
        "成交额": 806009472,
        "首次封板时间": "093012",
        "炸板次数": 0,
        "所属行业": "电子化学",
        "晋级概率_pct": 41.54,
        "题材簇": "磷化铟/半导体材料",
        "类似标的": "同线: 华正新材、宏昌电子、旭光电子 | 似近月龙头: 旭光电子"
      },
      {
        "代码": "600353",
        "名称": "旭光电子",
        "涨停原因": "氮化铝+韩国客户+真空灭弧室+可控核聚变",
        "连板数": 3,
        "晋级概率": 0.4153611787292111,
        "封单占比": "44.2%",
        "大单封板": "强封",
        "弱转强": "否",
        "涨跌幅": "9.99%",
        "最新价": 38.19,
        "换手率": "3.52%",
        "封板资金": "4.92亿",
        "成交额": 1113021728,
        "首次封板时间": "093035",
        "炸板次数": 0,
        "所属行业": "其他电子",
        "晋级概率_pct": 41.54,
        "题材簇": "磷化铟/半导体材料",
        "类似标的": "同线: 光华科技、华正新材、宏昌电子"
      },
      {
        "代码": "603618",
        "名称": "杭电股份",
        "涨停原因": "光纤涨价+铜箔+特高压",
        "连板数": 3,
        "晋级概率": 0.3845936840085288,
        "封单占比": "6.1%",
        "大单封板": "否",
        "弱转强": "否",
        "涨跌幅": "9.99%",
        "最新价": 51.73,
        "换手率": "4.48%",
        "封板资金": "9612.64万",
        "成交额": 1575478544,
        "首次封板时间": "093637",
        "炸板次数": 0,
        "所属行业": "电网设备",
        "晋级概率_pct": 38.46,
        "题材簇": "光纤/四氯化硅",
        "类似标的": "似近月龙头: 三孚股份、宏柏新材"
      },
      {
        "代码": "603115",
        "名称": "海星股份",
        "涨停原因": "AI服务器电极箔+市占率第一+业绩增长",
        "连板数": 3,
        "晋级概率": 0.3845936840085288,
        "封单占比": "5.2%",
        "大单封板": "否",
        "弱转强": "否",
        "涨跌幅": "10.00%",
        "最新价": 119.94,
        "换手率": "1.87%",
        "封板资金": "2746.63万",
        "成交额": 531354656,
        "首次封板时间": "093650",
        "炸板次数": 0,
        "所属行业": "元件",
        "晋级概率_pct": 38.46,
        "题材簇": "AI/算力/机器人",
        "类似标的": "同线: 艾华集团、鑫源智造 | 似近月龙头: 天娱数科"
      },
      {
        "代码": "000777",
        "名称": "中核科技",
        "涨停原因": "中核集团旗下+核电阀门+控股股东增持",
        "连板数": 3,
        "晋级概率": 0.3276168419331911,
        "封单占比": "4.6%",
        "大单封板": "否",
        "弱转强": "是",
        "涨跌幅": "10.02%",
        "最新价": 21.86,
        "换手率": "20.64%",
        "封板资金": "7841.84万",
        "成交额": 1701761984,
        "首次封板时间": "092500",
        "炸板次数": 2,
        "所属行业": "通用设备",
        "晋级概率_pct": 32.76,
        "题材簇": "行业:通用设备",
        "类似标的": "-"
      },
      {
        "代码": "603186",
        "名称": "华正新材",
        "涨停原因": "覆铜板+AI算力+定增扩产",
        "连板数": 3,
        "晋级概率": 0.3276168419331911,
        "封单占比": "1.0%",
        "大单封板": "否",
        "弱转强": "是",
        "涨跌幅": "10.00%",
        "最新价": 226.67,
        "换手率": "10.23%",
        "封板资金": "3538.32万",
        "成交额": 3603072160,
        "首次封板时间": "093256",
        "炸板次数": 33,
        "所属行业": "元件",
        "晋级概率_pct": 32.76,
        "题材簇": "磷化铟/半导体材料",
        "类似标的": "同线: 光华科技、宏昌电子、旭光电子 | 似近月龙头: 旭光电子"
      },
      {
        "代码": "603002",
        "名称": "宏昌电子",
        "涨停原因": "高速覆铜板+环氧树脂+先进封装",
        "连板数": 3,
        "晋级概率": 0.3276168419331911,
        "封单占比": "2.6%",
        "大单封板": "否",
        "弱转强": "是",
        "涨跌幅": "10.00%",
        "最新价": 23.2,
        "换手率": "6.92%",
        "封板资金": "4700.32万",
        "成交额": 1801844544,
        "首次封板时间": "093431",
        "炸板次数": 10,
        "所属行业": "电子化学",
        "晋级概率_pct": 32.76,
        "题材簇": "磷化铟/半导体材料",
        "类似标的": "同线: 光华科技、华正新材、旭光电子 | 似近月龙头: 旭光电子"
      },
      {
        "代码": "002080",
        "名称": "中材科技",
        "涨停原因": "特种电子布+风电叶片+央企背景",
        "连板数": 3,
        "晋级概率": 0.3276168419331911,
        "封单占比": "0.2%",
        "大单封板": "否",
        "弱转强": "是",
        "涨跌幅": "10.00%",
        "最新价": 82.41,
        "换手率": "4.92%",
        "封板资金": "1168.57万",
        "成交额": 6698619904,
        "首次封板时间": "094506",
        "炸板次数": 47,
        "所属行业": "玻璃玻纤",
        "晋级概率_pct": 32.76,
        "题材簇": "PCB/元件",
        "类似标的": "-"
      }
    ],
    "2": [
      {
        "代码": "603773",
        "名称": "沃格光电",
        "涨停原因": "TGV玻璃基板+先进封装+PET铜箔",
        "连板数": 2,
        "晋级概率": 0.2878934199797015,
        "封单占比": "14.4%",
        "大单封板": "是",
        "弱转强": "否",
        "涨跌幅": "10.00%",
        "最新价": 166.13,
        "换手率": "5.31%",
        "封板资金": "2.81亿",
        "成交额": 1950594960,
        "首次封板时间": "093914",
        "炸板次数": 0,
        "所属行业": "光学光电",
        "晋级概率_pct": 28.79,
        "题材簇": "磷化铟/半导体材料",
        "类似标的": "同线: 光华科技、华正新材、宏昌电子 | 似近月龙头: 旭光电子"
      },
      {
        "代码": "000679",
        "名称": "大连友谊",
        "涨停原因": "百货零售+大连地区+电商",
        "连板数": 2,
        "晋级概率": 0.28445155615028306,
        "封单占比": "17.9%",
        "大单封板": "是",
        "弱转强": "否",
        "涨跌幅": "10.03%",
        "最新价": 7.35,
        "换手率": "6.31%",
        "封板资金": "2830.61万",
        "成交额": 157769156,
        "首次封板时间": "130618",
        "炸板次数": 0,
        "所属行业": "一般零售",
        "晋级概率_pct": 28.45,
        "题材簇": "行业:一般零售",
        "类似标的": "-"
      },
      {
        "代码": "600192",
        "名称": "长城电工",
        "涨停原因": "输变电设备+核电+一带一路+国企改革",
        "连板数": 2,
        "晋级概率": 0.24857342686567163,
        "封单占比": "11.0%",
        "大单封板": "否",
        "弱转强": "是",
        "涨跌幅": "10.01%",
        "最新价": 8.35,
        "换手率": "6.66%",
        "封板资金": "2680.52万",
        "成交额": 243748936,
        "首次封板时间": "093122",
        "炸板次数": 3,
        "所属行业": "电网设备",
        "晋级概率_pct": 24.86,
        "题材簇": "行业:电网设备",
        "类似标的": "-"
      },
      {
        "代码": "600186",
        "名称": "莲花控股",
        "涨停原因": "算力+阶跃星辰投资+半导体材料+调味品龙头",
        "连板数": 2,
        "晋级概率": 0.24857342686567163,
        "封单占比": "1.9%",
        "大单封板": "否",
        "弱转强": "是",
        "涨跌幅": "9.98%",
        "最新价": 14.66,
        "换手率": "11.63%",
        "封板资金": "5748.95万",
        "成交额": 2988177536,
        "首次封板时间": "093633",
        "炸板次数": 8,
        "所属行业": "调味发酵",
        "晋级概率_pct": 24.86,
        "题材簇": "磷化铟/半导体材料",
        "类似标的": "同线: 光华科技、华正新材、宏昌电子 | 似近月龙头: 旭光电子"
      },
      {
        "代码": "002141",
        "名称": "贤丰控股",
        "涨停原因": "覆铜板+PCB上游+扭亏为盈",
        "连板数": 2,
        "晋级概率": 0.24857342686567163,
        "封单占比": "5.1%",
        "大单封板": "否",
        "弱转强": "是",
        "涨跌幅": "10.03%",
        "最新价": 4.28,
        "换手率": "16.09%",
        "封板资金": "3518.16万",
        "成交额": 687193168,
        "首次封板时间": "100554",
        "炸板次数": 6,
        "所属行业": "元件",
        "晋级概率_pct": 24.86,
        "题材簇": "磷化铟/半导体材料",
        "类似标的": "同线: 光华科技、华正新材、宏昌电子 | 似近月龙头: 旭光电子"
      },
      {
        "代码": "002989",
        "名称": "中天精装",
        "涨停原因": "FCBGA封装基板+HBM+半导体转型+浙江国资",
        "连板数": 2,
        "晋级概率": 0.24857342686567163,
        "封单占比": "0.8%",
        "大单封板": "否",
        "弱转强": "是",
        "涨跌幅": "10.01%",
        "最新价": 33.97,
        "换手率": "12.11%",
        "封板资金": "574.77万",
        "成交额": 739530528,
        "首次封板时间": "101718",
        "炸板次数": 17,
        "所属行业": "装修装饰",
        "晋级概率_pct": 24.86,
        "题材簇": "磷化铟/半导体材料",
        "类似标的": "同线: 光华科技、华正新材、宏昌电子 | 似近月龙头: 旭光电子"
      },
      {
        "代码": "600397",
        "名称": "江钨装备",
        "涨停原因": "钨钽铌并购+磁选装备+江西国资",
        "连板数": 2,
        "晋级概率": 0.24560164693772515,
        "封单占比": "0.0%",
        "大单封板": "否",
        "弱转强": "是",
        "涨跌幅": "10.01%",
        "最新价": 18.36,
        "换手率": "14.73%",
        "封板资金": "72.71万",
        "成交额": 2570234416,
        "首次封板时间": "131518",
        "炸板次数": 16,
        "所属行业": "专用设备",
        "晋级概率_pct": 24.56,
        "题材簇": "锆/小金属",
        "类似标的": "-"
      },
      {
        "代码": "600615",
        "名称": "鑫源智造",
        "涨停原因": "智能割草机器人+无人割草机+轻量化+比亚迪概念",
        "连板数": 2,
        "晋级概率": 0.24560164693772515,
        "封单占比": "1.1%",
        "大单封板": "否",
        "弱转强": "是",
        "涨跌幅": "9.96%",
        "最新价": 11.04,
        "换手率": "6.51%",
        "封板资金": "159.06万",
        "成交额": 151346554,
        "首次封板时间": "145008",
        "炸板次数": 1,
        "所属行业": "工业金属",
        "晋级概率_pct": 24.56,
        "题材簇": "AI/算力/机器人",
        "类似标的": "同线: 海星股份、艾华集团 | 似近月龙头: 天娱数科"
      },
      {
        "代码": "603989",
        "名称": "艾华集团",
        "涨停原因": "MLPC+AI服务器+铝电解电容+薄膜电容",
        "连板数": 2,
        "晋级概率": 0.24524254294567163,
        "封单占比": "12.2%",
        "大单封板": "是",
        "弱转强": "是",
        "涨跌幅": "10.00%",
        "最新价": 37.73,
        "换手率": "3.72%",
        "封板资金": "6685.90万",
        "成交额": 547646672,
        "首次封板时间": "093819",
        "炸板次数": 4,
        "所属行业": "元件",
        "晋级概率_pct": 24.52,
        "题材簇": "AI/算力/机器人",
        "类似标的": "同线: 海星股份、鑫源智造 | 似近月龙头: 天娱数科"
      }
    ]
  }
}